{
  "name": "ABS GF",
  "product_url": "https://eu.store.bambulab.com/de/products/abs-gf?id=48011475911004",
  "technical_data": {
    "Dry Out Before Use": "Recommended",
    "Dry Conditions": "80℃, 8h",
    "ACE Pro Compatibility": "Compatible",
    "Printing Temperature": "240-270℃",
    "Heated Bed Temperature": "80-100℃",
    "Printing Speed": "<180 mm/s",
    "Heat Deflection Temperature (0.45MPa)": "99°C",
    "Elongation at Break": "6.3%",
    "Properties": [
      "- Enhanced Strength and Stiffness",
      "- Greater Dimensional Stability",
      "- Fine Matte Finish",
      "- Durability and Water Resistance"
    ]
  },
  "ratings": {
    "impactStrength": 2,
    "stiffness": 3,
    "budgetFriendly": 7,
    "heatResistance": 6,
    "printability": 7
  }
}



