{
  "name": "PLA Matte",
  "product_url": "https://store.anycubic.com/products/matte-pla-filament",
  "technical_data": {
    "Dry Out Before Use": "Recommended",
    "Dry Conditions": "40℃-50℃, 6h-8h",
    "ACE Pro Compatibility": "Compatible",
    "Printing Temperature": "190-230℃",
    "Heated Bed Temperature": "55-65℃",
    "Printing Speed": "50-200mm/s",
    "Cooling Time": "8s",
    "Maximum Volumetric Flow Rate": "12mm/s",
    "Properties": [
      "- Soft texture, delicate surface, and seamless layer finish",
      "- Easy support removal",
      "- Can be stored for a long time",
      "- Eco-friendly and biodegradable"
    ]
  },
  "ratings": {
    "impactStrength": 4,
    "stiffness": 3,
    "budgetFriendly": 9,
    "heatResistance": 1,
    "printability": 10
  }
}


